Metadata-Version: 2.1
Name: emannotationschemas
Version: 5.13.0
Summary: a service for storing arbitrary annotation data on EM volumes stored in a cloud volume 
Home-page: https://github.com/fcollman/EMAnnotationSchemas
Author: Forrest Collman
Author-email: forrestc@alleninstitute.org
Requires-Python: >=3.8
License-File: LICENSE
Requires-Dist: marshmallow ==3.5.1
Requires-Dist: marshmallow-jsonschema ==0.10.0
Requires-Dist: numpy >=1.18.4
Requires-Dist: jsonschema <4.0
Requires-Dist: SQLAlchemy <1.4
Requires-Dist: shapely ==2.0.3
Requires-Dist: geoalchemy2 <0.12.0,>=0.11.1
Requires-Dist: flask-cors ==3.0.10
Provides-Extra: service
Requires-Dist: Flask ==2.1.3 ; extra == 'service'
Requires-Dist: psycopg2-binary ==2.9.1 ; extra == 'service'
Requires-Dist: flask-cors ==4.0.0 ; extra == 'service'
Requires-Dist: flask-admin ==1.6.1 ; extra == 'service'
Requires-Dist: flask-restx ==1.3.0 ; extra == 'service'
Requires-Dist: flask-accepts ==0.18.4 ; extra == 'service'
Requires-Dist: Werkzeug <=2.1.2 ; extra == 'service'
Requires-Dist: pandas ==2.0.3 ; extra == 'service'
